text_dedup/__init__.py
text_dedup/bloom_filter.py
text_dedup/minhash.py
text_dedup/py.typed
text_dedup/simhash.py
text_dedup/suffix_array.py
text_dedup/config/__init__.py
text_dedup/config/base.py
text_dedup/config/debug.py
text_dedup/config/algorithms/__init__.py
text_dedup/config/algorithms/base.py
text_dedup/config/algorithms/bloom.py
text_dedup/config/algorithms/minhash.py
text_dedup/config/algorithms/simhash.py
text_dedup/config/algorithms/suffix_array.py
text_dedup/config/io/__init__.py
text_dedup/config/io/input_configs.py
text_dedup/config/io/output_configs.py
text_dedup/data_sources/__init__.py
text_dedup/data_sources/io.py
text_dedup/utils/__init__.py
text_dedup/utils/env.py
text_dedup/utils/ftfy_utils.py
text_dedup/utils/hashfunc.py
text_dedup/utils/jaccard.py
text_dedup/utils/logger.py
text_dedup/utils/preprocess.py
text_dedup/utils/progress.py
text_dedup/utils/timer.py
text_dedup/utils/tokenization.py
text_dedup/utils/union_find.py
text_dedup-0.4.1.dist-info/METADATA
text_dedup-0.4.1.dist-info/WHEEL
text_dedup-0.4.1.dist-info/licenses/LICENSE
text_dedup-0.4.1.dist-info/RECORD
