Metadata-Version: 2.4
Name: text-dedup
Version: 0.4.1
Summary: All-in-one text deduplication tools
Project-URL: Documentation, https://ChenghaoMou.github.io/text-dedup/
Project-URL: Homepage, https://ChenghaoMou.github.io/text-dedup/
Project-URL: Repository, https://github.com/ChenghaoMou/text-dedup
Author-email: Chenghao Mou <mouchenghao@gmail.com>
License-File: LICENSE
Keywords: python
Classifier: Intended Audience :: Developers
Classifier: Programming Language :: Python
Classifier: Programming Language :: Python :: 3.12
Classifier: Programming Language :: Python :: 3.13
Classifier: Topic :: Software Development :: Libraries :: Python Modules
Requires-Python: <4.0,>=3.12
Requires-Dist: bitarray>=3.7.1
Requires-Dist: datasets>=4.0.0
Requires-Dist: ftfy>=6.3.1
Requires-Dist: numpy>=1.26.0
Requires-Dist: polars-grouper>=0.3.0
Requires-Dist: polars>=1.32.3
Requires-Dist: psutil>=5.9.0
Requires-Dist: pydantic-settings>=2.9.1
Requires-Dist: pydantic>=2.0.0
Requires-Dist: rbloom>=1.5.2
Requires-Dist: regex>=2024.11.6
Requires-Dist: rich>=13.0.0
Requires-Dist: scipy>=1.13.1
Requires-Dist: tqdm>=4.66.0
Requires-Dist: xxhash>=3.5.0
Provides-Extra: datasets
Provides-Extra: report
Requires-Dist: gradio-rangeslider>=0.0.8; extra == 'report'
Requires-Dist: gradio>=4.44.1; extra == 'report'
Requires-Dist: plotly>=6.1.1; extra == 'report'
